operations/__init__.py
operations/eigen_VV.py
operations/linear_regression.py
operations/svd.py
MNIST_Linear_Algebra-0.1.0.dist-info/METADATA
MNIST_Linear_Algebra-0.1.0.dist-info/WHEEL
MNIST_Linear_Algebra-0.1.0.dist-info/top_level.txt
MNIST_Linear_Algebra-0.1.0.dist-info/RECORD
