Metadata-Version: 2.1
Name: MNIST_Linear_Algebra
Version: 0.1.0
Summary: A package for performing linear algebra operations on the MNIST dataset.
Author: Sammy_IJ
Author-email: your.email@example.com
Classifier: Programming Language :: Python :: 3
Classifier: License :: OSI Approved :: MIT License
Classifier: Operating System :: OS Independent
Requires-Python: >=3.6
Requires-Dist: numpy
Requires-Dist: matplotlib
Requires-Dist: torch
Requires-Dist: torchvision
Requires-Dist: scikit-learn
